wrongbutusefulsbi/__init__.py
wrongbutusefulsbi/examples/__init__.py
wrongbutusefulsbi/examples/bvcbm.py
wrongbutusefulsbi/examples/contaminated_normal.py
wrongbutusefulsbi/examples/contaminated_slcp.py
wrongbutusefulsbi/examples/gaussian_vs_laplace.py
wrongbutusefulsbi/examples/misspec_ma1.py
wrongbutusefulsbi/examples/sir.py
wrongbutusefulsbi/examples/toad.py
wrongbutusefulsbi/examples/wright_fisher.py
wrongbutusefulsbi-0.0.8.dist-info/LICENSE
wrongbutusefulsbi-0.0.8.dist-info/METADATA
wrongbutusefulsbi-0.0.8.dist-info/WHEEL
wrongbutusefulsbi-0.0.8.dist-info/top_level.txt
wrongbutusefulsbi-0.0.8.dist-info/RECORD
