Metadata-Version: 2.1
Name: wrongbutusefulsbi
Version: 0.0.8
Home-page: https://github.com/RyanJafefKelly/wrongbutusefulsbi
Author: Ryan Kelly
Author-email: ryan@kiiii.com
License: GPLv3
Requires-Python: >=3.7
License-File: LICENSE
Requires-Dist: numpy >=1.12.1
Requires-Dist: scipy >=0.19
Requires-Dist: matplotlib >=1.1.1
Requires-Dist: numpyro >=0.2.4
Requires-Dist: jax >=0.2.4
Requires-Dist: jaxlib >=0.1.56
Requires-Dist: pandas >=1.0.1
Requires-Dist: seaborn >=0.11.1
Requires-Dist: arviz >=0.11.0
Requires-Dist: diffrax >=0.1.0
